.coveragerc
.gitignore
AUTHORS.rst
CHANGELOG.rst
LICENSE
README.rst
requirements.txt
setup.cfg
setup.py
docs/Makefile
docs/authors.rst
docs/changelog.rst
docs/conf.py
docs/index.rst
docs/license.rst
docs/_static/.gitignore
src/schwurbler/__init__.py
src/schwurbler/schwurbler.py
src/schwurbler.egg-info/PKG-INFO
src/schwurbler.egg-info/SOURCES.txt
src/schwurbler.egg-info/dependency_links.txt
src/schwurbler.egg-info/entry_points.txt
src/schwurbler.egg-info/not-zip-safe
src/schwurbler.egg-info/requires.txt
src/schwurbler.egg-info/top_level.txt
tests/conftest.py
tests/test_schwurbler.py