Metadata-Version: 1.1
Name: schwurbler
Version: 1.0.3
Summary: Mangle strings by repeated Google Translate
Home-page: https://github.com/Signaltonsalat/schwurbler
Author: Signaltonsalat
Author-email: signaltonsalat@gmail.com
License: GPL-2.0
Platform: any
Classifier: Development Status :: 4 - Beta
Classifier: Programming Language :: Python
